ColorCorrectionPipeline/__init__.py
ColorCorrectionPipeline/__version__.py
ColorCorrectionPipeline/config.py
ColorCorrectionPipeline/constants.py
ColorCorrectionPipeline/models.py
ColorCorrectionPipeline/pipeline.py
ColorCorrectionPipeline/core/__init__.py
ColorCorrectionPipeline/core/color_spaces.py
ColorCorrectionPipeline/core/correction.py
ColorCorrectionPipeline/core/metrics.py
ColorCorrectionPipeline/core/transforms.py
ColorCorrectionPipeline/core/utils.py
ColorCorrectionPipeline/flat_field/__init__.py
ColorCorrectionPipeline/flat_field/correction.py
ColorCorrectionPipeline/flat_field/models/__init__.py
ColorCorrectionPipeline/flat_field/models/plane_det_model_YOLO_512_n.pt
ColorCorrectionPipeline/io/__init__.py
ColorCorrectionPipeline/io/readers.py
ColorCorrectionPipeline/io/writers.py
colorcorrectionpipeline-1.3.3.dist-info/METADATA
colorcorrectionpipeline-1.3.3.dist-info/WHEEL
colorcorrectionpipeline-1.3.3.dist-info/licenses/LICENSE
colorcorrectionpipeline-1.3.3.dist-info/RECORD
