Metadata-Version: 2.4
Name: ColorCorrectionPipeline
Version: 1.3.3
Summary: A step-wise, color correction pipeline for digital images combining flat-field correction, gamma correction, white-balance, and color-correction
Project-URL: Homepage, https://github.com/collinswakholi/ColorCorrectionPackage
Project-URL: Repository, https://github.com/collinswakholi/ColorCorrectionPackage
Project-URL: Bug Tracker, https://github.com/collinswakholi/ColorCorrectionPackage/issues
Project-URL: Documentation, https://github.com/collinswakholi/ColorCorrectionPackage
Author: Collins Wakholi, Devin A. Rippner
License: MIT
License-File: LICENSE
Keywords: color-correction,computer-vision,flat-field,gamma-correction,image-processing,photography,scientific-imaging,white-balance
Classifier: Development Status :: 4 - Beta
Classifier: Intended Audience :: Developers
Classifier: Intended Audience :: Science/Research
Classifier: License :: OSI Approved :: MIT License
Classifier: Operating System :: OS Independent
Classifier: Programming Language :: Python :: 3
Classifier: Programming Language :: Python :: 3.9
Classifier: Programming Language :: Python :: 3.10
Classifier: Programming Language :: Python :: 3.11
Classifier: Programming Language :: Python :: 3.12
Classifier: Topic :: Scientific/Engineering :: Image Processing
Classifier: Topic :: Software Development :: Libraries :: Python Modules
Requires-Python: >=3.8
Requires-Dist: colour-science>=0.4.0
Requires-Dist: matplotlib>=3.4.0
Requires-Dist: numpy>=1.21.0
Requires-Dist: opencv-contrib-python>=4.5.0
Requires-Dist: opencv-python>=4.5.0
Requires-Dist: pandas>=1.3.0
Requires-Dist: plotly>=5.0.0
Requires-Dist: scikit-learn>=1.0.0
Requires-Dist: scipy>=1.7.0
Requires-Dist: seaborn>=0.11.0
Requires-Dist: torch>=1.10.0
Requires-Dist: ultralytics>=8.0.0
Provides-Extra: dev
Requires-Dist: black>=23.0; extra == 'dev'
Requires-Dist: hypothesis>=6.0; extra == 'dev'
Requires-Dist: mypy>=1.0; extra == 'dev'
Requires-Dist: pytest-cov>=4.0; extra == 'dev'
Requires-Dist: pytest>=7.0; extra == 'dev'
Requires-Dist: ruff>=0.1.0; extra == 'dev'
Provides-Extra: docs
Requires-Dist: sphinx-rtd-theme>=1.0; extra == 'docs'
Requires-Dist: sphinx>=5.0; extra == 'docs'
